pyx/__init__.py
pyx/__main__.py
pyx/errors.py
pyx/utils.py
pyx/tasks/__init__.py
pyx/tasks/new.py
pyx/tasks/release.py
pyx/tasks/run.py
pyx/tasks/test.py
pyx/tasks/version.py
pyx_manager-1.7.1.dist-info/METADATA
pyx_manager-1.7.1.dist-info/RECORD
pyx_manager-1.7.1.dist-info/WHEEL
pyx_manager-1.7.1.dist-info/entry_points.txt
pyx_manager-1.7.1.dist-info/top_level.txt
