Metadata-Version: 2.1
Name: pyx-manager
Version: 1.7.1
Summary: Command-line project manager
Home-page: https://github.com/Afoucaul/pyx
Author: Armand Foucault
Author-email: armand.foucault@telecom-bretagne.eu
License: UNKNOWN
Platform: UNKNOWN
Requires-Dist: docopt
Requires-Dist: colorama
Requires-Dist: twine
